<?xml version="1.0" encoding="UTF-8"?>
<MF0 version="1.1" packageUris="http://schema.mathworks.com/mf0/ci/19700101 http://schema.mathworks.com/mf0/sl_modelref_info/R2021a http://schema.mathworks.com/mf0/slexec_mm_sto/R2021a_202007071525">
  <ModelRefInfoRepo.ModelRefInfoRoot type="ModelRefInfoRepo.ModelRefInfoRoot" uuid="bc738d96-a499-4f81-8f67-fd2e6596e43d">
    <autoSolverStatusFlags>331</autoSolverStatusFlags>
    <childModelRefInfo type="ModelRefInfoRepo.ChildModelRefInfo" uuid="c7632e8e-b794-46c3-bea4-640ae5dabdb0">
      <modelName>forloop</modelName>
      <modelPath>forloop</modelPath>
    </childModelRefInfo>
    <dataTransferInfos>AAFJTQAAAAAOAAAAOAAAAAYAAAAIAAAAAgAAAAAAAAAFAAAACAAAAAAAAAABAAAAAQAAAAAAAAAFAAQAAQAAAAEAAAAAAAAA</dataTransferInfos>
    <defaultsCMapping>{&quot;Inports&quot;:&quot;{\&quot;Name\&quot;:\&quot;Default\&quot;,\&quot;Checksum\&quot;:\&quot;Default\&quot;,\&quot;PerInstancePropertiesChecksum\&quot;:\&quot;\&quot;,\&quot;MemorySectionName\&quot;:\&quot;None\&quot;,\&quot;MemorySectionChecksum\&quot;:\&quot;None\&quot;}&quot;,&quot;Outports&quot;:&quot;{\&quot;Name\&quot;:\&quot;Default\&quot;,\&quot;Checksum\&quot;:\&quot;Default\&quot;,\&quot;PerInstancePropertiesChecksum\&quot;:\&quot;\&quot;,\&quot;MemorySectionName\&quot;:\&quot;None\&quot;,\&quot;MemorySectionChecksum\&quot;:\&quot;None\&quot;}&quot;,&quot;ParameterArguments&quot;:&quot;{\&quot;Name\&quot;:\&quot;Default\&quot;,\&quot;Checksum\&quot;:\&quot;Default\&quot;,\&quot;PerInstancePropertiesChecksum\&quot;:\&quot;\&quot;,\&quot;MemorySectionName\&quot;:\&quot;None\&quot;,\&quot;MemorySectionChecksum\&quot;:\&quot;None\&quot;}&quot;,&quot;LocalParameters&quot;:&quot;{\&quot;Name\&quot;:\&quot;Default\&quot;,\&quot;Checksum\&quot;:\&quot;Default\&quot;,\&quot;PerInstancePropertiesChecksum\&quot;:\&quot;\&quot;,\&quot;MemorySectionName\&quot;:\&quot;None\&quot;,\&quot;MemorySectionChecksum\&quot;:\&quot;None\&quot;}&quot;,&quot;GlobalParameters&quot;:&quot;{\&quot;Name\&quot;:\&quot;Default\&quot;,\&quot;Checksum\&quot;:\&quot;Default\&quot;,\&quot;PerInstancePropertiesChecksum\&quot;:\&quot;\&quot;,\&quot;MemorySectionName\&quot;:\&quot;None\&quot;,\&quot;MemorySectionChecksum\&quot;:\&quot;None\&quot;}&quot;,&quot;InternalData&quot;:&quot;{\&quot;Name\&quot;:\&quot;Default\&quot;,\&quot;Checksum\&quot;:\&quot;Default\&quot;,\&quot;PerInstancePropertiesChecksum\&quot;:\&quot;\&quot;,\&quot;MemorySectionName\&quot;:\&quot;None\&quot;,\&quot;MemorySectionChecksum\&quot;:\&quot;None\&quot;}&quot;,&quot;SharedLocalDataStores&quot;:&quot;{\&quot;Name\&quot;:\&quot;Default\&quot;,\&quot;Checksum\&quot;:\&quot;Default\&quot;,\&quot;PerInstancePropertiesChecksum\&quot;:\&quot;\&quot;,\&quot;MemorySectionName\&quot;:\&quot;None\&quot;,\&quot;MemorySectionChecksum\&quot;:\&quot;None\&quot;}&quot;,&quot;GlobalDataStores&quot;:&quot;{\&quot;Name\&quot;:\&quot;Default\&quot;,\&quot;Checksum\&quot;:\&quot;Default\&quot;,\&quot;PerInstancePropertiesChecksum\&quot;:\&quot;\&quot;,\&quot;MemorySectionName\&quot;:\&quot;None\&quot;,\&quot;MemorySectionChecksum\&quot;:\&quot;None\&quot;}&quot;,&quot;Constants&quot;:&quot;{\&quot;Name\&quot;:\&quot;Default\&quot;,\&quot;Checksum\&quot;:\&quot;Default\&quot;,\&quot;PerInstancePropertiesChecksum\&quot;:\&quot;\&quot;,\&quot;MemorySectionName\&quot;:\&quot;None\&quot;,\&quot;MemorySectionChecksum\&quot;:\&quot;None\&quot;}&quot;,&quot;DataTransfers&quot;:&quot;{\&quot;Name\&quot;:\&quot;Default\&quot;,\&quot;Checksum\&quot;:\&quot;Default\&quot;,\&quot;PerInstancePropertiesChecksum\&quot;:\&quot;\&quot;,\&quot;MemorySectionName\&quot;:\&quot;None\&quot;,\&quot;MemorySectionChecksum\&quot;:\&quot;None\&quot;}&quot;,&quot;ModelData&quot;:&quot;{\&quot;Name\&quot;:\&quot;Default\&quot;,\&quot;Checksum\&quot;:\&quot;Default\&quot;,\&quot;PerInstancePropertiesChecksum\&quot;:\&quot;\&quot;,\&quot;MemorySectionName\&quot;:\&quot;None\&quot;,\&quot;MemorySectionChecksum\&quot;:\&quot;None\&quot;}&quot;,&quot;InitializeTerminate&quot;:&quot;{\&quot;Name\&quot;:\&quot;Default\&quot;,\&quot;Checksum\&quot;:\&quot;Default\&quot;,\&quot;PerInstancePropertiesChecksum\&quot;:\&quot;\&quot;,\&quot;MemorySectionName\&quot;:\&quot;None\&quot;,\&quot;MemorySectionChecksum\&quot;:\&quot;None\&quot;}&quot;,&quot;Execution&quot;:&quot;{\&quot;Name\&quot;:\&quot;Default\&quot;,\&quot;Checksum\&quot;:\&quot;Default\&quot;,\&quot;PerInstancePropertiesChecksum\&quot;:\&quot;\&quot;,\&quot;MemorySectionName\&quot;:\&quot;None\&quot;,\&quot;MemorySectionChecksum\&quot;:\&quot;None\&quot;}&quot;,&quot;SharedUtility&quot;:&quot;{\&quot;Name\&quot;:\&quot;Default\&quot;,\&quot;Checksum\&quot;:\&quot;Default\&quot;,\&quot;PerInstancePropertiesChecksum\&quot;:\&quot;\&quot;,\&quot;MemorySectionName\&quot;:\&quot;None\&quot;,\&quot;MemorySectionChecksum\&quot;:\&quot;None\&quot;}&quot;}</defaultsCMapping>
    <fundamentalSampleTimePeriod>.2</fundamentalSampleTimePeriod>
    <hasBlockWithPeriodicDiscreteSampleTime>true</hasBlockWithPeriodicDiscreteSampleTime>
    <hasBwsAccessed>true</hasBwsAccessed>
    <hasBwsAccessedByAnyModel>true</hasBwsAccessedByAnyModel>
    <hasNonVirtualConstantTs>true</hasNonVirtualConstantTs>
    <inports type="ModelRefInfoRepo.InportInformation" uuid="32256619-10bb-4cbb-b875-5a369350da3a">
      <isNotDerivPort>true</isNotDerivPort>
      <designMax>Inf</designMax>
      <designMin>-Inf</designMin>
      <indexType>2</indexType>
      <rateInfo type="ModelRefInfoRepo.RateInfo">
        <compiled>true</compiled>
        <nonFcnCallPartitionName>D1</nonFcnCallPartitionName>
        <period>.2</period>
        <priority>40</priority>
        <rateIdx>0</rateIdx>
      </rateInfo>
      <resolvedSignalObject></resolvedSignalObject>
      <sigNameToEMVCEMap type="ModelRefInfoRepo.SigNameEMVCEInfo" uuid="93222945-99cb-4386-a0c4-6aec9823231c"/>
    </inports>
    <isBdInSimModeForSimCodegenVariants>false</isBdInSimModeForSimCodegenVariants>
    <isInlineParamsOn>true</isInlineParamsOn>
    <isOrigInportVirtualBus>false</isOrigInportVirtualBus>
    <isOrigOutportVirtualBus>false</isOrigOutportVirtualBus>
    <loggingSaveFormat>2</loggingSaveFormat>
    <maxFreqHz>-1.0</maxFreqHz>
    <numDStateRecs>1</numDStateRecs>
    <numDataInputPorts>1</numDataInputPorts>
    <numLoggableDStateRecs>1</numLoggableDStateRecs>
    <numLoggableJacobianDStates>0</numLoggableJacobianDStates>
    <origInportBusType></origInportBusType>
    <origOutportBusOutputAsStruct>false</origOutportBusOutputAsStruct>
    <origOutportBusType></origOutportBusType>
    <outports type="ModelRefInfoRepo.OutportInformation" uuid="79363d4f-243d-4a29-b14d-f8bf6c397ba5">
      <hasSystemInitMethod>true</hasSystemInitMethod>
      <isInitializedWithIC>true</isInitializedWithIC>
      <designMax>Inf</designMax>
      <designMin>-Inf</designMin>
      <rateInfo type="ModelRefInfoRepo.RateInfo">
        <compiled>true</compiled>
        <nonFcnCallPartitionName>D1</nonFcnCallPartitionName>
        <period>.2</period>
        <priority>40</priority>
        <rateIdx>0</rateIdx>
      </rateInfo>
      <resolvedSignalObject></resolvedSignalObject>
      <sigNameToEMVCEMap type="ModelRefInfoRepo.SigNameEMVCEInfo" uuid="be834946-3343-4048-ac41-f5e601d1430f"/>
    </outports>
    <removeResetFunc>true</removeResetFunc>
    <runtimeNonFcnCallRateInfos type="ModelRefInfoRepo.RateInfo">
      <compiled>true</compiled>
      <nonFcnCallPartitionName>D1</nonFcnCallPartitionName>
      <period>.2</period>
      <priority>40</priority>
      <rateIdx>0</rateIdx>
    </runtimeNonFcnCallRateInfos>
    <sampleTimeInheritanceRule>1</sampleTimeInheritanceRule>
    <timingAndTaskingRegistry>&lt;?xml version=&quot;1.0&quot;?&gt;
&lt;slexec_sto version=&quot;1.1&quot; packageUris=&quot;http://schema.mathworks.com/mf0/slexec_mm_sto/R2021a_202007071525&quot;&gt;
  &lt;sto.Registry type=&quot;sto.Registry&quot; uuid=&quot;ce42d8c8-7195-4d62-8a35-f75b3fa65597&quot;&gt;
    &lt;clocks type=&quot;sto.Timer&quot; uuid=&quot;7afc3e2b-6561-464c-9c53-2f67001f26a9&quot;&gt;
      &lt;computedFundamentalDiscretePeriod&gt;.2&lt;/computedFundamentalDiscretePeriod&gt;
      &lt;resolution&gt;.2&lt;/resolution&gt;
      &lt;clockTickConstraint&gt;PeriodicWithFixedResolution&lt;/clockTickConstraint&gt;
      &lt;timeAdvanceMode&gt;FixedStep&lt;/timeAdvanceMode&gt;
      &lt;clockDomain type=&quot;sto.ClockDomain&quot; uuid=&quot;da4cd797-e5d3-452d-9e18-fc1d358bd396&quot;&gt;
        &lt;baseTaskID&gt;_task0&lt;/baseTaskID&gt;
        &lt;rates type=&quot;sto.Rate&quot; uuid=&quot;d9241e1d-09fb-41da-8e0c-51177281ef97&quot;/&gt;
        &lt;rootTaskHierarchyElements type=&quot;sto.Task&quot; uuid=&quot;f903d055-2772-4990-b086-b4ef50401e0f&quot;&gt;
          &lt;isExecutable&gt;true&lt;/isExecutable&gt;
          &lt;orderIndex&gt;1&lt;/orderIndex&gt;
          &lt;rates type=&quot;sto.Rate&quot; uuid=&quot;d9241e1d-09fb-41da-8e0c-51177281ef97&quot;&gt;
            &lt;annotation&gt;D1&lt;/annotation&gt;
            &lt;colorIndex&gt;2&lt;/colorIndex&gt;
            &lt;description&gt;Discrete 1&lt;/description&gt;
            &lt;eventSourceType&gt;UNSPECIFIED_EVENT_SOURCE&lt;/eventSourceType&gt;
            &lt;registry type=&quot;sto.Registry&quot; uuid=&quot;ce42d8c8-7195-4d62-8a35-f75b3fa65597&quot;/&gt;
            &lt;taskId&gt;_task0&lt;/taskId&gt;
            &lt;rateSpec type=&quot;sto.RateSpec&quot; uuid=&quot;8f4243ff-8ad7-4dbc-b51d-05fa7337db99&quot;&gt;
              &lt;period&gt;.2&lt;/period&gt;
              &lt;rateType&gt;ClassicPeriodicDiscrete&lt;/rateType&gt;
            &lt;/rateSpec&gt;
          &lt;/rates&gt;
          &lt;elementType&gt;Task&lt;/elementType&gt;
          &lt;identifier&gt;_task0&lt;/identifier&gt;
          &lt;priority&gt;40&lt;/priority&gt;
        &lt;/rootTaskHierarchyElements&gt;
      &lt;/clockDomain&gt;
    &lt;/clocks&gt;
    &lt;clocks type=&quot;sto.Event&quot; uuid=&quot;e9838d1b-4500-434d-9347-85413b0e6573&quot;&gt;
      &lt;clientId&gt;NonTunableParameterChangeEvent&lt;/clientId&gt;
      &lt;eventType&gt;UNSPECIFIED_EVENT_SOURCE&lt;/eventType&gt;
      &lt;cNum&gt;2&lt;/cNum&gt;
      &lt;clockType&gt;Event&lt;/clockType&gt;
      &lt;identifier&gt;NonTunableParameterChangeEvent&lt;/identifier&gt;
      &lt;specifiedTaskingMode&gt;ExplicitTasking&lt;/specifiedTaskingMode&gt;
      &lt;timeAdvanceMode&gt;None&lt;/timeAdvanceMode&gt;
      &lt;clockDomain type=&quot;sto.ClockDomain&quot; uuid=&quot;a1de3ebf-6bab-421a-bbad-8f90d779de8a&quot;/&gt;
    &lt;/clocks&gt;
    &lt;clocks type=&quot;sto.Event&quot; uuid=&quot;65e0b623-7471-4e6e-a4fa-0daaea5cf2d6&quot;&gt;
      &lt;clientId&gt;ParameterChangeEvent&lt;/clientId&gt;
      &lt;eventType&gt;PARAMETER_CHANGE_EVENT&lt;/eventType&gt;
      &lt;cNum&gt;1&lt;/cNum&gt;
      &lt;clockType&gt;Event&lt;/clockType&gt;
      &lt;identifier&gt;ParameterChangeEvent&lt;/identifier&gt;
      &lt;specifiedTaskingMode&gt;ExplicitTasking&lt;/specifiedTaskingMode&gt;
      &lt;timeAdvanceMode&gt;None&lt;/timeAdvanceMode&gt;
      &lt;clockDomain type=&quot;sto.ClockDomain&quot; uuid=&quot;b8a560cd-7b2e-49c9-a228-fec29fa8359b&quot;&gt;
        &lt;rates type=&quot;sto.Rate&quot; uuid=&quot;97ae1603-dfd6-4429-a727-f1338505b780&quot;/&gt;
        &lt;rootTaskHierarchyElements type=&quot;sto.Task&quot; uuid=&quot;9eefcc54-1a2e-4b2f-8ddd-7b13a9037293&quot;&gt;
          &lt;isExplicit&gt;true&lt;/isExplicit&gt;
          &lt;rates type=&quot;sto.Rate&quot; uuid=&quot;97ae1603-dfd6-4429-a727-f1338505b780&quot;&gt;
            &lt;eventSourceType&gt;PARAMETER_CHANGE_EVENT&lt;/eventSourceType&gt;
            &lt;rateIDX&gt;-1&lt;/rateIDX&gt;
            &lt;registry type=&quot;sto.Registry&quot; uuid=&quot;ce42d8c8-7195-4d62-8a35-f75b3fa65597&quot;/&gt;
            &lt;stringID&gt;ParameterChangeEvent&lt;/stringID&gt;
            &lt;taskId&gt;ModelWideParameterChangeEvent&lt;/taskId&gt;
            &lt;useForExecution&gt;NotForExecution&lt;/useForExecution&gt;
            &lt;rateSpec type=&quot;sto.RateSpec&quot; uuid=&quot;15814335-223b-4ecb-a3e6-c2f0c8c815b0&quot;&gt;
              &lt;period&gt;Inf&lt;/period&gt;
              &lt;rateType&gt;ModelWideParameterChangeEvent&lt;/rateType&gt;
            &lt;/rateSpec&gt;
          &lt;/rates&gt;
          &lt;tNum&gt;1&lt;/tNum&gt;
          &lt;elementType&gt;Task&lt;/elementType&gt;
          &lt;identifier&gt;ModelWideParameterChangeEvent&lt;/identifier&gt;
          &lt;priority&gt;-1&lt;/priority&gt;
          &lt;schedulingClockID&gt;ParameterChangeEvent&lt;/schedulingClockID&gt;
        &lt;/rootTaskHierarchyElements&gt;
      &lt;/clockDomain&gt;
    &lt;/clocks&gt;
    &lt;executionSpec&gt;Undetermined&lt;/executionSpec&gt;
    &lt;taskDependencyGraph type=&quot;sto.SerializedTaskConnectionList&quot; uuid=&quot;7fd9ed06-c02e-468b-bebd-c2e8b7b51d2a&quot;&gt;
      &lt;taskIdentifier&gt;_task0&lt;/taskIdentifier&gt;
    &lt;/taskDependencyGraph&gt;
    &lt;taskDependencyGraph type=&quot;sto.SerializedTaskConnectionList&quot; uuid=&quot;7519d6d4-bb8b-407c-a90b-f5086f5be3cc&quot;&gt;
      &lt;clockIdentifier&gt;ParameterChangeEvent&lt;/clockIdentifier&gt;
      &lt;taskIdentifier&gt;ModelWideParameterChangeEvent&lt;/taskIdentifier&gt;
    &lt;/taskDependencyGraph&gt;
    &lt;taskPriorityDirection&gt;HighNumberLast&lt;/taskPriorityDirection&gt;
    &lt;tasks type=&quot;sto.Task&quot; uuid=&quot;f903d055-2772-4990-b086-b4ef50401e0f&quot;/&gt;
    &lt;tasks type=&quot;sto.Task&quot; uuid=&quot;9eefcc54-1a2e-4b2f-8ddd-7b13a9037293&quot;/&gt;
    &lt;timeAdvanceMode&gt;FixedStep&lt;/timeAdvanceMode&gt;
  &lt;/sto.Registry&gt;
&lt;/slexec_sto&gt;</timingAndTaskingRegistry>
    <zeroInternalMemoryAtStartupUnchecked>true</zeroInternalMemoryAtStartupUnchecked>
    <FMUBlockMap type="ModelRefInfoRepo.FMUBlockInfo" uuid="e1ae00a9-89df-47f9-b5e2-24968b2095b5"/>
    <codeGenInfo type="ModelRefInfoRepo.CodeGenInformation" uuid="5fc88fa4-87ca-4ac8-9e5a-498472879f07"/>
    <configSettingsForConsistencyChecks type="ModelRefInfoRepo.ConfigSettingsForConsistencyChecks" uuid="71470e45-071b-43ae-86fe-dc226e2ae2c9">
      <consistentOutportInitialization>true</consistentOutportInitialization>
      <fixedStepSize>.2</fixedStepSize>
      <frameDiagnosticSetting>2</frameDiagnosticSetting>
      <hasHybridSampleTime>true</hasHybridSampleTime>
      <optimizedInitCode>true</optimizedInitCode>
      <signalLoggingSaveFormat>2</signalLoggingSaveFormat>
      <simSIMDOptimization>1</simSIMDOptimization>
      <solverName>FixedStepDiscrete</solverName>
      <solverType>SOLVER_TYPE_FIXEDSTEP</solverType>
      <hardwareSettings type="ModelRefInfoRepo.HardwareSettings" uuid="118fb5f6-f123-4785-b4cd-d450c8cffcbc">
        <prodBitPerChar>8</prodBitPerChar>
        <prodBitPerDouble>64</prodBitPerDouble>
        <prodBitPerFloat>32</prodBitPerFloat>
        <prodBitPerInt>32</prodBitPerInt>
        <prodBitPerLong>32</prodBitPerLong>
        <prodBitPerLongLong>64</prodBitPerLongLong>
        <prodBitPerPointer>64</prodBitPerPointer>
        <prodBitPerPtrDiffT>64</prodBitPerPtrDiffT>
        <prodBitPerShort>16</prodBitPerShort>
        <prodBitPerSizeT>64</prodBitPerSizeT>
        <prodEndianess>1</prodEndianess>
        <prodShiftRight>true</prodShiftRight>
        <prodWordSize>64</prodWordSize>
      </hardwareSettings>
    </configSettingsForConsistencyChecks>
    <controllableInputRatesMap type="ModelRefInfoRepo.VarTsUIDMap" uuid="0b17f515-ea2c-4758-b5f5-0a1d84ce16e7"/>
    <controllableOutputRatesMap type="ModelRefInfoRepo.VarTsUIDMap" uuid="d517a87e-3fcb-4eb4-b780-77c63787df95"/>
    <dataPortGroup type="ModelRefInfoRepo.DataPortGroup" uuid="91dd3011-eea6-4ed2-a78c-7e1cd9583f33">
      <compDataInputPorts>0</compDataInputPorts>
      <compDataOutputPorts>0</compDataOutputPorts>
      <dataInputPorts>0</dataInputPorts>
      <dataOutputPorts>0</dataOutputPorts>
    </dataPortGroup>
    <expFcnUnconnectedDataPortGroup type="ModelRefInfoRepo.DataPortGroup" uuid="f90ca1f0-0f35-4840-9fdd-82ac776eec84"/>
    <interfaceParameterInfo type="ModelRefInfoRepo.InterfaceParameterInfo" uuid="00afa107-21dd-4afc-b68a-65da9249a08e"/>
    <messageInfo type="ModelRefInfoRepo.MessageInformation" uuid="18a0b86a-d4ea-4982-9462-874df0f90a77"/>
    <methodInfo type="ModelRefInfoRepo.MethodExistenceInfo" uuid="af481078-dd5c-44d5-843c-efe4a92be84e">
      <hasSystemInitializeMethod>true</hasSystemInitializeMethod>
      <hasSystemResetMethod>true</hasSystemResetMethod>
      <hasTerminateMethod>true</hasTerminateMethod>
      <hasUpdateMethod>true</hasUpdateMethod>
    </methodInfo>
    <periodicEventPortUnsupportedBlockInfo type="ModelRefInfoRepo.PeriodicEventPortUnsupportedBlockInfo" uuid="d5762e0f-8960-4263-ae83-17969658198b"/>
    <portGroupsRequireSameRate type="ModelRefInfoRepo.PortGroupsRequireSameRate" uuid="12ccb660-e23b-407f-9d59-1ef244e3c95a">
      <DSMPortGroups type="ModelRefInfoRepo.NameToPortGroupIdxVectMap" uuid="7d6e997a-afb2-4662-9255-f8707bc2df99"/>
      <GlobalDSMPortGroups type="ModelRefInfoRepo.NameToPortGroupIdxVectMap" uuid="32dae61a-4f38-4626-b85a-05892477b1f8"/>
      <mergedPortGroups type="ModelRefInfoRepo.NameToPortGroupIdxVectMap" uuid="e54fcdfc-5d48-4866-85e9-ce7a69fe9425"/>
    </portGroupsRequireSameRate>
    <rateBasedMdlGlobalDSMRateSpec type="ModelRefInfoRepo.GlobalDSMRateSpecMap" uuid="5ddd00d1-7930-4ac0-9677-7fcb0ae9e842"/>
    <rateSpecOfGlobalDSMAccessedByDescExpFcnMdlMap type="ModelRefInfoRepo.GlobalDSMRateSpecMap" uuid="65da53b7-0d76-4fb5-8bc6-47f3a16008c0"/>
    <rootBlockDiagramInterface type="ci.Model" uuid="4848b7e3-383f-4c75-9ae2-f74672e82a4e">
      <p_RootComponentInterface type="ci.ComponentInterface" uuid="0fa6073f-de75-4fa0-89fc-4e4ce35062dc">
        <p_InputPorts type="ci.SignalInterface" uuid="a6afc4d6-c3ba-4628-96ed-03c46380e47d">
          <p_ComputedNumericDimensions>1.0</p_ComputedNumericDimensions>
          <p_ComputedSampleTime>.2</p_ComputedSampleTime>
          <p_ComputedSampleTime>0.0</p_ComputedSampleTime>
          <p_ComputedType>uint16</p_ComputedType>
        </p_InputPorts>
        <p_Name>forloop</p_Name>
        <p_OutputPorts type="ci.SignalInterface" uuid="a5dcb8f5-7de4-42aa-87d4-0f2d2a6c7e84">
          <p_ComputedNumericDimensions>1.0</p_ComputedNumericDimensions>
          <p_ComputedSampleTime>.2</p_ComputedSampleTime>
          <p_ComputedSampleTime>0.0</p_ComputedSampleTime>
          <p_ComputedType>uint16</p_ComputedType>
        </p_OutputPorts>
        <p_Type>ROOT</p_Type>
      </p_RootComponentInterface>
    </rootBlockDiagramInterface>
    <simulinkFunctions type="ModelRefInfoRepo.SimulinkFunctions" uuid="6f47a50b-c54f-4b23-a1a6-0638f93b9bfe">
      <compSimulinkFunctionCatalog></compSimulinkFunctionCatalog>
    </simulinkFunctions>
    <stateWriterToOwnerMap type="ModelRefInfoRepo.StateWriterInfo" uuid="e1897d42-330a-46ba-b073-5816ac0e7dbf"/>
    <stoClientDataRegistry type="sto.ClientDataRegistry" uuid="a12ad4cd-1129-4a2a-a704-170c2384c5a5">
      <dataSets type="sto.ClientClockNamedDataSet" uuid="e3219159-9980-4ff2-888e-a0b6e20362e8">
        <tag>sltpEvents</tag>
      </dataSets>
      <dataSets type="sto.ClientTaskHierarchyElementNamedDataSet" uuid="3b72b45f-7ef8-47ba-aa93-304cf3b463d2">
        <tag>sltpTaskGroups</tag>
      </dataSets>
      <dataSets type="sto.ClientTaskHierarchyElementNamedDataSet" uuid="c458e5f3-0674-4aa4-a9a2-06a744ed6d50">
        <dSet type="ModelRefInfoRepo.SltpTaskData" uuid="b914c655-e921-451f-b5b3-668ba18ede49"/>
        <tSet type="ModelRefInfoRepo.SltpTaskData" uuid="b914c655-e921-451f-b5b3-668ba18ede49">
          <dataName>D1</dataName>
          <linkedSet type="sto.ClientTaskHierarchyElementNamedDataSet" uuid="c458e5f3-0674-4aa4-a9a2-06a744ed6d50"/>
          <id type="sto.TaskHierarchyElementId">
            <id>_task0</id>
          </id>
        </tSet>
        <tag>sltpTasks</tag>
      </dataSets>
    </stoClientDataRegistry>
    <varTsUIDMap type="ModelRefInfoRepo.VarTsUIDMap" uuid="9e6022a1-9037-4e99-a0cb-db92f0f4a19a"/>
  </ModelRefInfoRepo.ModelRefInfoRoot>
</MF0>